waze_logger/__init__.py
waze_logger/__main__.py
waze_logger/location.py
waze_logger/route.py
waze_logger/waze_api.py
waze_logger/database/__init__.py
waze_logger/database/create.py
waze_logger/database/engine.py
waze_logger-0.1.0.dist-info/LICENSE
waze_logger-0.1.0.dist-info/METADATA
waze_logger-0.1.0.dist-info/WHEEL
waze_logger-0.1.0.dist-info/entry_points.txt
waze_logger-0.1.0.dist-info/top_level.txt
waze_logger-0.1.0.dist-info/RECORD
