Metadata-Version: 2.1
Name: waze-logger
Version: 0.1.0
Summary: A cli tool to log waze trop duration in a database. Ment to be used in a CRON schedule
Author-email: Felix Cusson <felixcusson@gmail.com>
Maintainer-email: Felix Cusson <felixcusson@gmail.com>
License: MIT License
Project-URL: Homepage, https://github.com/fcusson/waze_logger
Project-URL: Bug Reports, https://github.com/fcusson/waze_logger/issues
Project-URL: Source, https://github.com/fcusson/waze_logger
Keywords: waze,api,database,cron
Requires-Python: >=3.9
License-File: LICENSE
Requires-Dist: requests >=2.28.1
Requires-Dist: SQLAlchemy >=2.0.22
Requires-Dist: mysql-connector-python >=8.1.0
Provides-Extra: dev
Requires-Dist: pylint ; extra == 'dev'
Requires-Dist: radon ; extra == 'dev'
Requires-Dist: autopep8 ; extra == 'dev'
Requires-Dist: debugpy ; extra == 'dev'
Requires-Dist: build ; extra == 'dev'
Requires-Dist: coverage ; extra == 'dev'
